dwtls/__init__.py
dwtls/dwt_layers.py
dwtls-1.0.2.dist-info/LICENSE
dwtls-1.0.2.dist-info/METADATA
dwtls-1.0.2.dist-info/WHEEL
dwtls-1.0.2.dist-info/top_level.txt
dwtls-1.0.2.dist-info/RECORD
