Metadata-Version: 2.1
Name: dwtls
Version: 1.0.2
Summary: A library of trainable and fixed discrete wavelet transform layers
Home-page: https://github.com/TomohikoNakamura/dwtls
Author: Tomohiko Nakamura
Author-email: tomohiko.nakamura.jp@ieee.org
License: MIT
Platform: UNKNOWN
Classifier: Operating System :: OS Independent
Classifier: Programming Language :: Python :: 3
Classifier: License :: OSI Approved :: MIT License
Classifier: Topic :: Scientific/Engineering
Classifier: Topic :: Software Development
Classifier: Intended Audience :: Science/Research
Classifier: Intended Audience :: Developers
Requires-Python: >=3.7
License-File: LICENSE
Requires-Dist: numpy
Requires-Dist: torch
